README.md
setup.py
detectorpy/__init__.py
detectorpy/model.py
detectorpy.egg-info/PKG-INFO
detectorpy.egg-info/SOURCES.txt
detectorpy.egg-info/dependency_links.txt
detectorpy.egg-info/requires.txt
detectorpy.egg-info/top_level.txt
detectorpy/analysis/__init__.py
detectorpy/analysis/visualize.py
detectorpy/data/__init__.py
detectorpy/data/dataset.py
detectorpy/data/transforms/__init__.py
detectorpy/data/transforms/blur.py
detectorpy/data/transforms/crop.py
detectorpy/data/transforms/flip.py
detectorpy/data/transforms/rescale.py
detectorpy/data/transforms/rotate.py