Metadata-Version: 2.1
Name: detectorpy
Version: 1.0.5
Summary: A model to detect images
Home-page: UNKNOWN
Author: Kunal Singh
Author-email: ksingh19136@gmail.com
License: GPLv3
Platform: UNKNOWN
Classifier: License :: OSI Approved :: GNU General Public License v3 (GPLv3)
Classifier: Programming Language :: Python :: 3
Classifier: Programming Language :: Python :: 3.8
